rustcrateregex/Cargo.toml
rustcrateregex/LICENSE
rustcrateregex/README.MD
rustcrateregex/__init__.py
rustcrateregex/lib.rs
rustcrateregex/requirements.txt
rustcrateregex/rustregex.pyx
rustcrateregex/rustregex_compile.py
rustcrateregex/thirdparty.json
rustcrateregex-1.0.6.dist-info/LICENSE.rst
rustcrateregex-1.0.6.dist-info/METADATA
rustcrateregex-1.0.6.dist-info/WHEEL
rustcrateregex-1.0.6.dist-info/top_level.txt
rustcrateregex-1.0.6.dist-info/RECORD
